odoo/addons/account_invoice_select_for_payment/README.rst
odoo/addons/account_invoice_select_for_payment/__init__.py
odoo/addons/account_invoice_select_for_payment/__manifest__.py
odoo/addons/account_invoice_select_for_payment/i18n/account_invoice_select_for_payment.pot
odoo/addons/account_invoice_select_for_payment/i18n/es.po
odoo/addons/account_invoice_select_for_payment/i18n/it.po
odoo/addons/account_invoice_select_for_payment/i18n/sv.po
odoo/addons/account_invoice_select_for_payment/models/__init__.py
odoo/addons/account_invoice_select_for_payment/models/account_move.py
odoo/addons/account_invoice_select_for_payment/readme/CONTRIBUTORS.md
odoo/addons/account_invoice_select_for_payment/readme/CREDITS.md
odoo/addons/account_invoice_select_for_payment/readme/DESCRIPTION.md
odoo/addons/account_invoice_select_for_payment/readme/USAGE.md
odoo/addons/account_invoice_select_for_payment/static/description/icon.png
odoo/addons/account_invoice_select_for_payment/static/description/index.html
odoo/addons/account_invoice_select_for_payment/tests/__init__.py
odoo/addons/account_invoice_select_for_payment/tests/test_account_invoice_select_for_payment.py
odoo/addons/account_invoice_select_for_payment/views/account_move.xml
odoo_addon_account_invoice_select_for_payment-18.0.1.0.0.3.dist-info/METADATA
odoo_addon_account_invoice_select_for_payment-18.0.1.0.0.3.dist-info/WHEEL
odoo_addon_account_invoice_select_for_payment-18.0.1.0.0.3.dist-info/top_level.txt
odoo_addon_account_invoice_select_for_payment-18.0.1.0.0.3.dist-info/RECORD
